Metadata-Version: 2.1
Name: StreamingApplicationDQ
Version: 1.1
Summary: Streaming application with unit testing
Home-page: UNKNOWN
Author: 
Author-email: 
License: UNKNOWN
Platform: UNKNOWN
